[
  {
    "id": "a01",
    "name": "Diane Dieter",
    "email": "d.dieter@email.com",
    "level": "superwizard",
    "age": "22",
    "status": "active"
  },
  {
    "id": "a02",
    "name": "Andrew Anderson",
    "email": "a.anderson@email.com",
    "level": "novice",
    "age": "25",
    "status": "disabled"
  },
  {
    "id": "a03",
    "name": "Mark Mathew",
    "email": "m.mathew@email.com",
    "level": "Wizard",
    "age": "27",
    "status": "active"
  },
  {
    "id": "a04",
    "name": "Andreea Antoni",
    "email": "a.antoni@email.com",
    "level": "novice",
    "age": "20",
    "status": "active"
  },
  {
    "id": "a05",
    "name": "Helena Hilview",
    "email": "h.hilview@email.com",
    "level": "apprentice",
    "age": "20",
    "status": "disabled"
  }
]
